snake_game/__init__.py
snake_game/board.py
snake_game/direction.py
snake_game/food.py
snake_game/main.py
snake_game/snake.py
tests/__init__.py
tests/test_board.py
tests/test_direction.py
tests/test_food.py
tests/test_game.py
tests/test_snake.py
snake_game_tk-0.1.2.dist-info/METADATA
snake_game_tk-0.1.2.dist-info/WHEEL
snake_game_tk-0.1.2.dist-info/entry_points.txt
snake_game_tk-0.1.2.dist-info/top_level.txt
snake_game_tk-0.1.2.dist-info/RECORD
