Metadata-Version: 2.1
Name: snake-game-tk
Version: 0.1.2
Summary: A simple Snake game using Tkinter
Home-page: https://github.com/lvidarte/snake_game
Author: Leo Vidarte
Author-email: lvidarte@gmail.com
Classifier: Programming Language :: Python :: 3
Classifier: License :: OSI Approved :: MIT License
Classifier: Operating System :: OS Independent
Requires-Python: >=3.6
